moodleinspire/VERSION
moodleinspire/__init__.py
moodleinspire/chart.py
moodleinspire/evaluation.py
moodleinspire/prediction.py
moodleinspire/training.py
moodleinspire/version.py
moodleinspire/classifier/__init__.py
moodleinspire/classifier/tensor.py
moodleinspire/processor/__init__.py
moodleinspire/processor/binary.py
moodleinspire/processor/estimator.py
moodleinspire-0.0.10.dist-info/DESCRIPTION.rst
moodleinspire-0.0.10.dist-info/METADATA
moodleinspire-0.0.10.dist-info/RECORD
moodleinspire-0.0.10.dist-info/WHEEL
moodleinspire-0.0.10.dist-info/metadata.json
moodleinspire-0.0.10.dist-info/top_level.txt
